cli/__init__.py
cli/_version.py
cli/attachment.py
cli/colors.py
cli/config.py
cli/connect.py
cli/debug.py
cli/dispatch.py
cli/editor.py
cli/engine.py
cli/login.py
cli/model.py
cli/pneumo.py
cli/policy.py
cli/profile.py
cli/run.py
cli/schema.py
cli/sensor.py
cli/snapshot.py
cli/stats.py
cli/stream.py
cli/version.py
cli/auth/__init__.py
cli/auth/basicauth.py
cli/auth/ldap.py
cli/auth/oauth2.py
cli/auth/sessioncookie.py
cli/monitor/__init__.py
cli/monitor/layout.py
cli/monitor/monitor.py
cli/monitor/stable.py
cli/monitor/terminal.py
etc/bash_completion.d/fastscore
fastscore_cli-1.10.3.dist-info/LICENSE
fastscore_cli-1.10.3.dist-info/METADATA
fastscore_cli-1.10.3.dist-info/WHEEL
fastscore_cli-1.10.3.dist-info/entry_points.txt
fastscore_cli-1.10.3.dist-info/top_level.txt
fastscore_cli-1.10.3.dist-info/RECORD
